hpctasks/__init__.py
hpctasks/module.py
hpctasks/slurm.py
scriptengine_tasks_hpc-1.0.0.dist-info/LICENSE
scriptengine_tasks_hpc-1.0.0.dist-info/METADATA
scriptengine_tasks_hpc-1.0.0.dist-info/WHEEL
scriptengine_tasks_hpc-1.0.0.dist-info/entry_points.txt
scriptengine_tasks_hpc-1.0.0.dist-info/top_level.txt
scriptengine_tasks_hpc-1.0.0.dist-info/RECORD
